sqlalchemy_tx_context/__init__.py
sqlalchemy_tx_context/context.py
sqlalchemy_tx_context/exceptions.py
sqlalchemy_tx_context/py.typed
sqlalchemy_tx_context-1.0.1.dist-info/licenses/LICENSE
sqlalchemy_tx_context-1.0.1.dist-info/METADATA
sqlalchemy_tx_context-1.0.1.dist-info/WHEEL
sqlalchemy_tx_context-1.0.1.dist-info/top_level.txt
sqlalchemy_tx_context-1.0.1.dist-info/RECORD
