Metadata-Version: 2.4
Name: sqlalchemy_tx_context
Version: 1.0.1
Summary: Context-local session manager for SQLAlchemy AsyncSession
Author-email: QuisEgoSum <subbotin.evdokim@gmail.com>
License-Expression: MIT
Project-URL: Homepage, https://github.com/QuisEgoSum/sqlalchemy-tx-context
Project-URL: Repository, https://github.com/QuisEgoSum/sqlalchemy-tx-context
Project-URL: Documentation, https://github.com/QuisEgoSum/sqlalchemy-tx-context#readme
Keywords: sqlalchemy,async,contextvars,transaction,session
Classifier: Programming Language :: Python :: 3
Classifier: Programming Language :: Python :: 3.9
Classifier: Programming Language :: Python :: 3.10
Classifier: Programming Language :: Python :: 3.11
Classifier: Programming Language :: Python :: 3.12
Classifier: Operating System :: OS Independent
Classifier: Development Status :: 5 - Production/Stable
Requires-Python: >=3.9
License-File: LICENSE
Requires-Dist: SQLAlchemy>=2.0.0
Provides-Extra: dev
Requires-Dist: pytest<9.0,>=8.0; extra == "dev"
Requires-Dist: pytest-asyncio>=1.0.0; extra == "dev"
Requires-Dist: tox>=4.26.0; extra == "dev"
Requires-Dist: pytest-cov<7.0,>=6.0; extra == "dev"
Requires-Dist: ruff>=0.11.2; extra == "dev"
Requires-Dist: black>=25.1.0; extra == "dev"
Requires-Dist: build>=1.2.2; extra == "dev"
Requires-Dist: twine>=6.1.0; extra == "dev"
Requires-Dist: asyncpg>=0.29.0; extra == "dev"
Requires-Dist: aiosqlite>=0.21.0; extra == "dev"
Requires-Dist: pyright>=1.1.402; extra == "dev"
Dynamic: license-file
